{
  "nav_label": "Blog",
  "title": "Research Log",
  "subtitle": "Stories, experiments, and longer reflections from ongoing projects.",
  "kicker": "Lab notebook",
  "archive_label": "View all posts",
  "page_labels": {
    "back": "Back to site",
    "search": "Search posts...",
    "allTags": "All topics",
    "empty": "No posts published yet.",
    "darkToLight": "Switch to light mode",
    "lightToDark": "Switch to dark mode"
  },
  "post_labels": {
    "backBlog": "Back to blog",
    "backHome": "Home",
    "bottomBackBlog": "Back to blog index",
    "bottomBackHome": "Return to homepage",
    "darkToLight": "Switch to light mode",
    "lightToDark": "Switch to dark mode",
    "updated": "Updated",
    "reading": "read",
    "missing": "We could not find this article. Please check the URL or return to the blog index."
  },
  "blogs": [
    {
      "title": "HK Weather",
      "summary": "Real-time Hong Kong weather monitoring and forecast application with interactive visualizations and detailed meteorological data.",
      "image": "./images/Weather.png",
      "post_time": "2024-08-15",
      "author": "Haozhou Xu",
      "tags": [
        "Web Development",
        "Data Visualization",
        "Weather"
      ],
      "links": [
        {
          "type": "Website",
          "url": "./HKWeather/HK.html"
        }
      ]
    },
    {
      "title": "Photo Gallery",
      "summary": "A personal photography portfolio showcasing travel and landscape photography from around the world.",
      "image": "./images/photogallery.png",
      "post_time": "2024-07-20",
      "author": "Haozhou Xu",
      "tags": [
        "Photography",
        "Portfolio",
        "Art"
      ],
      "links": [
        {
          "type": "Gallery",
          "url": "./PhotoGallery/index.html"
        }
      ]
    }
  ]
}
